snap_plugin_collector_pysmart-2.dist-info/DESCRIPTION.rst
snap_plugin_collector_pysmart-2.dist-info/METADATA
snap_plugin_collector_pysmart-2.dist-info/RECORD
snap_plugin_collector_pysmart-2.dist-info/WHEEL
snap_plugin_collector_pysmart-2.dist-info/entry_points.txt
snap_plugin_collector_pysmart-2.dist-info/metadata.json
snap_plugin_collector_pysmart-2.dist-info/top_level.txt
snap_pysmart/__init__.py
snap_pysmart/_version.py
snap_pysmart/plugin.py
