Metadata-Version: 2.0
Name: snap-plugin-collector-pysmart
Version: 2
Summary: This is a plugin for the Snap telemetry framework providingstorage related metrics through smartmontools
Home-page: http://github.com/intelsdi-x/snap-plugin-collector-pysmart
Author: Joel Cooklin
Author-email: joel.cooklin@gmail.com
License: Apache 2.0
Keywords: snap telemetry plugin plugins metrics smartmon smartmontools
Platform: UNKNOWN
Requires-Dist: pySMART.smartx (>=0.3.6)
Requires-Dist: shutilwhich (>=1.1.0)
Requires-Dist: snap-plugin-lib-py (>=1.0.10,<2)
